finfest_quant_open_toolbox/__init__.py
finfest_quant_open_toolbox/toolbox.py
finfest_quant_open_toolbox/update_check.py
finfest_quant_open_toolbox-0.0.2.dist-info/LICENSE
finfest_quant_open_toolbox-0.0.2.dist-info/METADATA
finfest_quant_open_toolbox-0.0.2.dist-info/WHEEL
finfest_quant_open_toolbox-0.0.2.dist-info/top_level.txt
finfest_quant_open_toolbox-0.0.2.dist-info/RECORD
