Metadata-Version: 2.1
Name: finfest-quant-open-toolbox
Version: 0.0.2
Summary: Toolbox for Auquan's Finfest Open
Home-page: UNKNOWN
Author: Auquan Team
Author-email: qqadmins@auquan.com
License: MIT
Keywords: auquan finance trading backtesting development
Platform: UNKNOWN
Classifier: Development Status :: 5 - Production/Stable
Classifier: Intended Audience :: Developers
Classifier: Topic :: Software Development :: Build Tools
Classifier: License :: OSI Approved :: MIT License
Classifier: Programming Language :: Python :: 3.6
Requires-Dist: numpy
Requires-Dist: pandas
Requires-Dist: scipy
Requires-Dist: sklearn
